midi2mqtt/__init__.py
midi2mqtt/midi2mqtt.py
midi2mqtt-0.0.4.dist-info/entry_points.txt
midi2mqtt-0.0.4.dist-info/WHEEL
midi2mqtt-0.0.4.dist-info/METADATA
midi2mqtt-0.0.4.dist-info/RECORD
