Metadata-Version: 2.1
Name: midi2mqtt
Version: 0.0.4
Summary: Receive MIDI signals and forward them to a mqtt broker.
Home-page: https://github.com/pintman/midi2mqtt
License: MIT
Keywords: mqtt,midi
Author: Pintman
Author-email: pintman@0xabc.de
Requires-Python: >=3.7,<4.0
Classifier: Development Status :: 3 - Alpha
Classifier: License :: OSI Approved :: MIT License
Classifier: Programming Language :: Python :: 3
Classifier: Programming Language :: Python :: 3.10
Classifier: Programming Language :: Python :: 3.7
Classifier: Programming Language :: Python :: 3.8
Classifier: Programming Language :: Python :: 3.9
Requires-Dist: paho-mqtt (>=1.6.0,<2.0.0)
Requires-Dist: python-rtmidi (>=1.4.9,<2.0.0)
Project-URL: Repository, https://github.com/pintman/midi2mqtt
